{
  "include": ["instawow"],
  "exclude": ["instawow/migrations"],
  "ignore": [],
  "strict": [],
  "typeshedPath": "./.py-types/typeshed",
  "stubPath": "./.py-types/stubs",
  "[venvPath]": "",
  "[venv]": "",
  "[verboseOutput]": false,
  "[pythonVersion]": "",
  "[pythonPlatform]": "",
  "executionEnvironments": [],
  "typeCheckingMode": "basic",
  "useLibraryCodeForTypes": true,
  "strictListInference": true,
  "strictDictionaryInference": true,
  "strictParameterNoneValue": true,
  "enableTypeIgnoreComments": true,
  "reportGeneralTypeIssues": true,
  "reportMissingImports": true,
  "reportMissingModuleSource": "warning",
  "reportMissingTypeStubs": false,
  "reportImportCycles": false,
  "reportUnusedImport": true,
  "reportUnusedClass": true,
  "reportUnusedFunction": "warning",
  "reportUnusedVariable": true,
  "reportDuplicateImport": true,
  "reportOptionalSubscript": true,
  "reportOptionalMemberAccess": true,
  "reportOptionalCall": true,
  "reportOptionalIterable": true,
  "reportOptionalContextManager": true,
  "reportOptionalOperand": true,
  "reportUntypedFunctionDecorator": "warning",
  "reportUntypedClassDecorator": "warning",
  "reportUntypedBaseClass": "warning",
  "reportUntypedNamedTuple": "warning",
  "reportPrivateUsage": "warning",
  "reportConstantRedefinition": "warning",
  "reportIncompatibleMethodOverride": false,
  "reportIncompatibleVariableOverride": true,
  "reportInvalidStringEscapeSequence": "warning",
  "reportUnknownParameterType": "warning",
  "reportUnknownArgumentType": "warning",
  "reportUnknownLambdaType": "warning",
  "reportUnknownVariableType": "warning",
  "reportUnknownMemberType": "warning",
  "reportCallInDefaultInitializer": false,
  "reportUnnecessaryIsInstance": "warning",
  "reportUnnecessaryCast": "warning",
  "reportAssertAlwaysTrue": "warning",
  "reportSelfClsParameterName": "warning",
  "reportImplicitStringConcatenation": false,
  "reportUndefinedVariable": true,
  "reportUnboundVariable": true,
  "reportInvalidStubStatement": false
}
